Metadata-Version: 2.1
Name: samplefit
Version: 0.3.1
Summary: samplefit library implements the Sample Fit Reliability algorithm for the assessment of sample fit in econometric models.
Home-page: https://github.com/okasag/samplefit
Download-URL: https://github.com/okasag/samplefit/archive/v0.3.1.tar.gz
Author: Gabriel Okasa and Kenneth A. Younge
Author-email: okasa.gabriel@gmail.com
License: MIT
Keywords: sample fit,reliability,econometrics
Platform: UNKNOWN
Classifier: Development Status :: 4 - Beta
Classifier: Intended Audience :: Science/Research
Classifier: Topic :: Software Development :: Build Tools
Classifier: License :: OSI Approved :: MIT License
Classifier: Programming Language :: Python :: 3.8
Classifier: Programming Language :: Python :: 3.9
Classifier: Programming Language :: Python :: 3.10
License-File: LICENSE
